client_of_redundant_servers/__init__.py
client_of_redundant_servers/client_of_redundant_ad_ldap_servers.py
client_of_redundant_servers/client_of_redundant_radius_servers.py
client_of_redundant_servers/client_of_redundant_servers.py
client_of_redundant_servers/dictionary.minimal
client_of_redundant_servers-0.6.dist-info/LICENSE.txt
client_of_redundant_servers-0.6.dist-info/METADATA
client_of_redundant_servers-0.6.dist-info/RECORD
client_of_redundant_servers-0.6.dist-info/WHEEL
client_of_redundant_servers-0.6.dist-info/top_level.txt
