Metadata-Version: 2.1
Name: client-of-redundant-servers
Version: 0.6
Summary: Client of redundant servers
Home-page: https://github.com/rbricheno/client_of_redundant_servers
Author: Robert Bricheno
License: UNKNOWN
Project-URL: Bug Reports, https://github.com/rbricheno/client_of_redundant_servers/issues
Project-URL: Source, https://github.com/rbricheno/client_of_redundant_servers
Keywords: redundant client radius ldap
Platform: UNKNOWN
Classifier: Development Status :: 3 - Alpha
Classifier: Intended Audience :: Developers
Classifier: Topic :: Software Development :: Libraries :: Python Modules
Classifier: License :: OSI Approved :: MIT License
Classifier: Programming Language :: Python :: 3
Classifier: Programming Language :: Python :: 3.4
Classifier: Programming Language :: Python :: 3.5
Classifier: Programming Language :: Python :: 3.6
Requires-Python: >=3
